LICENSE
MANIFEST.in
README.rst
requirements.txt
setup.cfg
setup.py
ckanext/__init__.py
ckanext/dataontosearch/__init__.py
ckanext/dataontosearch/auth.py
ckanext/dataontosearch/logic.py
ckanext/dataontosearch/plugin.py
ckanext/dataontosearch/utils.py
ckanext/dataontosearch/templates-search/dataontosearch_search.html
ckanext/dataontosearch/templates-search/snippets/search_form.html
ckanext/dataontosearch/templates-tagger/dataontosearch_tagger_edit.html
ckanext/dataontosearch/templates-tagger/dataontosearch_tagger_show.html
ckanext/dataontosearch/templates-tagger/package/edit_base.html
ckanext/dataontosearch/templates-tagger/package/read_base.html
ckanext/dataontosearch/tests/__init__.py
ckanext/dataontosearch/tests/test_plugin.py
ckanext/dataontosearch/views/__init__.py
ckanext/dataontosearch/views/search.py
ckanext/dataontosearch/views/tagger.py
ckanext/dataontosearch/views/utils.py
ckanext_dataontosearch.egg-info/PKG-INFO
ckanext_dataontosearch.egg-info/SOURCES.txt
ckanext_dataontosearch.egg-info/dependency_links.txt
ckanext_dataontosearch.egg-info/entry_points.txt
ckanext_dataontosearch.egg-info/namespace_packages.txt
ckanext_dataontosearch.egg-info/top_level.txt