Metadata-Version: 1.1
Name: ckanext-dataontosearch
Version: 0.0.6
Summary: Integration of an externally running DataOntoSearch instance, providing dataset tagging and search
Home-page: https://github.com/tobinus/ckanext-dataontosearch
Author: Thorben Werner Sjøstrøm Dahl
Author-email: thorben@sjostrom.no
License: AGPL
Keywords: CKAN search ontology
Platform: UNKNOWN
Classifier: Development Status :: 4 - Beta
Classifier: License :: OSI Approved :: GNU Affero General Public License v3 or later (AGPLv3+)
Classifier: Programming Language :: Python :: 2.7
